CHANGELOG.md
gest/GES-131.onnx
gest/__init__.py
gest/annotation/__init__.py
gest/annotation/capture.py
gest/annotation/gesture/__init__.py
gest/annotation/gesture/base.py
gest/annotation/gesture/closed_pinch.py
gest/annotation/gesture/open_pinch.py
gest/annotation/gesture/static.py
gest/annotation/review.py
gest/cv_gui.py
gest/demo.py
gest/examples/__init__.py
gest/examples/two_handed_scroll_and_click.py
gest/inference.py
gest/math.py
gest/pipeline.py
gest-0.3.0.dist-info/LICENSE
gest-0.3.0.dist-info/WHEEL
gest-0.3.0.dist-info/METADATA
gest-0.3.0.dist-info/RECORD
