Metadata-Version: 2.1
Name: gest
Version: 0.3.0
Summary: Hand gestures as an input device
Home-page: https://github.com/bm371613/gest/
License: GPL-3.0
Author: Bartosz Marcinkowski
Author-email: b.marcinkowski@leomail.pl
Requires-Python: >=3.6.1,<4.0.0
Classifier: License :: OSI Approved :: GNU General Public License v3 (GPLv3)
Classifier: Programming Language :: Python :: 3
Classifier: Programming Language :: Python :: 3.7
Classifier: Programming Language :: Python :: 3.8
Classifier: Programming Language :: Python :: 3.9
Requires-Dist: numpy
Requires-Dist: onnxruntime (>=1.4.0,<2.0.0)
Requires-Dist: opencv-python (>=4.4.0,<5.0.0)
Requires-Dist: pynput
Project-URL: Repository, https://github.com/bm371613/gest/
